gbsc_dnanexus/__init__.py
gbsc_dnanexus/utils.py
gbsc_dnanexus/scripts/__init__.py
gbsc_dnanexus/scripts/invite_user_to_projects.py
scgpm_lims/__init__.py
scgpm_lims/addruntotestdata.py
scgpm_lims/regeneratetestdata.py
scgpm_lims/components/__init__.py
scgpm_lims/components/connection.py
scgpm_lims/components/local.py
scgpm_lims/components/models.py
scgpm_lims/components/remote.py
scgpm_lims/scripts/__init__.py
scgpm_lims/scripts/create_sample_sheet.py
scgpm_lims/scripts/get_run_name_from_flowcell.py
scgpm_lims/scripts/start_analyses.py
scgpm_lims/test/__init__.py
scgpm_lims/test/test_models.py
scgpm_seqresults_dnanexus/__init__.py
scgpm_seqresults_dnanexus/dnanexus_utils.py
scgpm_seqresults_dnanexus/log.py
scgpm_seqresults_dnanexus/picard_tools.py
scgpm_seqresults_dnanexus/scripts/__init__.py
scgpm_seqresults_dnanexus/scripts/accept_pending_transfers.py
scgpm_seqresults_dnanexus/scripts/add_props_to_fq_files.py
scgpm_seqresults_dnanexus/scripts/add_props_to_project.py
scgpm_seqresults_dnanexus/scripts/add_r1-r2_fastq_paths.py
scgpm_seqresults_dnanexus/scripts/add_standard_props_to_projects.py
scgpm_seqresults_dnanexus/scripts/batch_download_fastqs.py
scgpm_seqresults_dnanexus/scripts/download_fastqs.py
scgpm_seqresults_dnanexus/scripts/download_multiple_projects.py
scgpm_seqresults_dnanexus/scripts/download_project.py
scgpm_seqresults_dnanexus/scripts/list_projects.py
scgpm_seqresults_dnanexus/scripts/scgpm_clean_raw_data.py
scgpm_seqresults_dnanexus/scripts/wrapper_download_project.py
scgpm_seqresults_dnanexus-0.5.0.data/scripts/accept_pending_transfers.py
scgpm_seqresults_dnanexus-0.5.0.data/scripts/add_props_to_fq_files.py
scgpm_seqresults_dnanexus-0.5.0.data/scripts/add_props_to_project.py
scgpm_seqresults_dnanexus-0.5.0.data/scripts/add_r1-r2_fastq_paths.py
scgpm_seqresults_dnanexus-0.5.0.data/scripts/add_standard_props_to_projects.py
scgpm_seqresults_dnanexus-0.5.0.data/scripts/batch_download_fastqs.py
scgpm_seqresults_dnanexus-0.5.0.dist-info/LICENSE.txt
scgpm_seqresults_dnanexus-0.5.0.dist-info/METADATA
scgpm_seqresults_dnanexus-0.5.0.dist-info/WHEEL
scgpm_seqresults_dnanexus-0.5.0.dist-info/top_level.txt
scgpm_seqresults_dnanexus-0.5.0.dist-info/RECORD
