Metadata-Version: 2.1
Name: scgpm-seqresults-dnanexus
Version: 0.5.0
Summary: Utilities for working with the Stanford Genome Sequencing Service Center (GSSC) application logic on DNAnexus.
Home-page: https://github.com/StanfordBioinformatics/scgpm_seqresults_dnanexus.git
Author: Nathaniel Watson
Author-email: nathankw@stanford.edu
License: UNKNOWN
Project-URL: Read the Docs, https://scgpm-seqresults-dnanexus.readthedocs.io/en/latest
Platform: UNKNOWN
Classifier: Programming Language :: Python :: 3
Classifier: License :: OSI Approved :: MIT License
Classifier: Operating System :: OS Independent
Requires-Dist: dxpy3
